cap2_assembly/__init__.py
cap2_assembly/cap2_assembly.py
cap2_assembly/cli.py
cap2_assembly-0.2.0.dist-info/AUTHORS.rst
cap2_assembly-0.2.0.dist-info/LICENSE
cap2_assembly-0.2.0.dist-info/METADATA
cap2_assembly-0.2.0.dist-info/WHEEL
cap2_assembly-0.2.0.dist-info/entry_points.txt
cap2_assembly-0.2.0.dist-info/top_level.txt
cap2_assembly-0.2.0.dist-info/RECORD
