Metadata-Version: 2.1
Name: cap2-assembly
Version: 0.2.0
Summary: Minimum viable module for the de novo assembly stage of metagenomics analysis.
Home-page: https://github.com/lauren-mak/cap2_assembly
Author: Lauren Mak
Author-email: laurenmak93@gmail.com
License: MIT license
Keywords: cap2_assembly
Platform: UNKNOWN
Classifier: Development Status :: 2 - Pre-Alpha
Classifier: Intended Audience :: Developers
Classifier: License :: OSI Approved :: MIT License
Classifier: Natural Language :: English
Classifier: Programming Language :: Python :: 3
Classifier: Programming Language :: Python :: 3.6
Classifier: Programming Language :: Python :: 3.7
Classifier: Programming Language :: Python :: 3.8
Requires-Python: >=3.6
License-File: LICENSE
License-File: AUTHORS.rst
Requires-Dist: Click (>=7.0)
